celeste_cohere/__init__.py
celeste_cohere/py.typed
celeste_cohere/chat/__init__.py
celeste_cohere/chat/client.py
celeste_cohere/chat/config.py
celeste_cohere/chat/parameters.py
celeste_cohere/chat/streaming.py
celeste_cohere-0.3.6.dist-info/METADATA
celeste_cohere-0.3.6.dist-info/WHEEL
celeste_cohere-0.3.6.dist-info/RECORD
